teloclip/__init__.py
teloclip/_version.py
teloclip/analysis.py
teloclip/cli.py
teloclip/extension.py
teloclip/extract_io.py
teloclip/logs.py
teloclip/motifs.py
teloclip/samops.py
teloclip/seqops.py
teloclip/streaming_analysis.py
teloclip/streaming_io.py
teloclip/utils.py
teloclip/commands/__init__.py
teloclip/commands/extend.py
teloclip/commands/extract.py
teloclip/commands/filter.py
teloclip-0.3.4.dist-info/METADATA
teloclip-0.3.4.dist-info/WHEEL
teloclip-0.3.4.dist-info/entry_points.txt
teloclip-0.3.4.dist-info/licenses/LICENSE
teloclip-0.3.4.dist-info/RECORD
