Metadata-Version: 2.4
Name: teloclip
Version: 0.3.4
Summary: A tool for the recovery of unassembled telomeres from raw long-reads using soft-clipped read alignments.
Project-URL: documentation, https://github.com/adamtaranto/teloclip
Project-URL: homepage, https://github.com/adamtaranto/teloclip
Project-URL: repository, https://github.com/adamtaranto/teloclip
Author: Adam Taranto
License: GPL-3.0-or-later
License-File: LICENSE
Classifier: Intended Audience :: Science/Research
Classifier: Programming Language :: Python :: 3
Classifier: Topic :: Scientific/Engineering :: Bio-Informatics
Requires-Python: >=3.8
Requires-Dist: biopython
Requires-Dist: click
Requires-Dist: pyfaidx
Requires-Dist: pysam
Requires-Dist: rich
Provides-Extra: dev
Requires-Dist: hatch; extra == 'dev'
Requires-Dist: ipykernel; extra == 'dev'
Requires-Dist: isort; extra == 'dev'
Requires-Dist: numpydoc-validation; extra == 'dev'
Requires-Dist: pre-commit; extra == 'dev'
Requires-Dist: pytest; extra == 'dev'
Requires-Dist: pytest-cov; extra == 'dev'
Requires-Dist: ruff; extra == 'dev'
